open_serializer/__init__.py
open_serializer/serialization/__init__.py
open_serializer/serialization/general.py
open_serializer/serialization/handler.py
open_serializer/serialization/helpers.py
open_serializer/utils/__init__.py
open_serializer/utils/dict_ops.py
open_serializer-0.0.5.dist-info/LICENSE
open_serializer-0.0.5.dist-info/METADATA
open_serializer-0.0.5.dist-info/WHEEL
open_serializer-0.0.5.dist-info/top_level.txt
open_serializer-0.0.5.dist-info/RECORD
