Metadata-Version: 2.1
Name: open-serializer
Version: 0.0.5
Summary: python object serializer
Home-page: https://github.com/Janus-Shiau/open-serializer
Author: Jia-Yau Shiau
Author-email: jiayau.shiau@gmail.com
License: LICENSE
Requires-Python: >=3.7
License-File: LICENSE
Requires-Dist: rich
Requires-Dist: ruamel.yaml
Requires-Dist: toml
